ssmash/__init__.py
ssmash/cli.py
ssmash/config.py
ssmash/converter.py
ssmash/custom_resources.py
ssmash/invalidation.py
ssmash/loader.py
ssmash/util.py
ssmash/yamlhelper.py
ssmash-2.2.0.dist-info/AUTHORS.rst
ssmash-2.2.0.dist-info/LICENSE
ssmash-2.2.0.dist-info/METADATA
ssmash-2.2.0.dist-info/WHEEL
ssmash-2.2.0.dist-info/entry_points.txt
ssmash-2.2.0.dist-info/top_level.txt
ssmash-2.2.0.dist-info/RECORD
