Metadata-Version: 2.1
Name: ssmash
Version: 2.2.0
Summary: SSM AppConfig Storage Helper
Home-page: https://github.com/garyd203/ssmash
Author: Gary Donovan
Author-email: gazza@gazza.id.au
License: GNU Affero General Public License v3
Project-URL: Documentation, https://ssmash.readthedocs.io/en/latest/
Project-URL: Source, https://github.com/garyd203/ssmash
Project-URL: Tracker, https://github.com/garyd203/ssmash/issues
Keywords: ssmash application-configuration configuration AWS cloudformation infrastructure-as-code
Platform: UNKNOWN
Classifier: Development Status :: 5 - Production/Stable
Classifier: Environment :: Console
Classifier: Intended Audience :: Developers
Classifier: License :: OSI Approved :: GNU Affero General Public License v3
Classifier: Natural Language :: English
Classifier: Operating System :: OS Independent
Classifier: Programming Language :: Python
Classifier: Programming Language :: Python :: 3
Classifier: Programming Language :: Python :: 3.6
Classifier: Programming Language :: Python :: 3.7
Classifier: Topic :: Software Development
Classifier: Topic :: System :: Systems Administration
Requires-Dist: click (<8,>=7.0)
Requires-Dist: PyYAML (<5.2,>=5.1)
Requires-Dist: flying-circus (<0.8,>=0.7)
Requires-Dist: inflection (==0.3.1)
